woodsman/__init__.py
woodsman/main.py
woodsman-0.1.2.dist-info/METADATA
woodsman-0.1.2.dist-info/WHEEL
woodsman-0.1.2.dist-info/entry_points.txt
woodsman-0.1.2.dist-info/licenses/LICENSE
woodsman-0.1.2.dist-info/RECORD
