Metadata-Version: 2.4
Name: woodsman
Version: 0.1.2
Summary: Woodsman is a generic SQL database viewer Inspired by Kino's iconic weapon, it empowers users to navigate, explore, and export SQL databases (SQLite and PostgreSQL) with interactive data exploration, filtering, and export capabilities.
Author-email: Ali Tavallaie <a.tavallaie@gmail.com>
License: MIT License
License-File: LICENSE
Requires-Python: >=3.10
Requires-Dist: sqlalchemy>=2.0.38
Requires-Dist: streamlit-extras>=0.5.5
Requires-Dist: streamlit>=1.42.1
Requires-Dist: tabulate>=0.9.0
